setup.cfg
setup.py
PySQLParser.egg-info/PKG-INFO
PySQLParser.egg-info/SOURCES.txt
PySQLParser.egg-info/dependency_links.txt
PySQLParser.egg-info/top_level.txt
pysqlparser/__init__.py
pysqlparser/ddlparser.py
pysqlparser/lexer.py
pysqlparser/parsetab.py
pysqlparser/ply/__init__.py
pysqlparser/ply/cpp.py
pysqlparser/ply/ctokens.py
pysqlparser/ply/lex.py
pysqlparser/ply/yacc.py
pysqlparser/ply/ygen.py