Metadata-Version: 1.0
Name: PySQLParser
Version: 0.1.3
Summary: Python SQL parser
Home-page: UNKNOWN
Author: Mika Lackman
Author-email: mika.lackman@gmail.com
License: LGPL
Platform: UNKNOWN
